{
  "people": [
    {
      "id": "tom-brady",
      "name": "Tom Brady",
      "aliases": [],
      "categories": [
        "Any Famous Person",
        "Athletes",
        "Football"
      ],
      "letters": {
        "first": "T",
        "last": "B"
      },
      "difficulty": 2,
      "image": null,
      "wiki": null
    },
    {
      "id": "peyton-manning",
      "name": "Peyton Manning",
      "aliases": [],
      "categories": [
        "Any Famous Person",
        "Athletes",
        "Football"
      ],
      "letters": {
        "first": "P",
        "last": "M"
      },
      "difficulty": 2,
      "image": null,
      "wiki": null
    },
    {
      "id": "joe-montana",
      "name": "Joe Montana",
      "aliases": [],
      "categories": [
        "Any Famous Person",
        "Athletes",
        "Football"
      ],
      "letters": {
        "first": "J",
        "last": "M"
      },
      "difficulty": 2,
      "image": null,
      "wiki": null
    },
    {
      "id": "cam-newton",
      "name": "Cam Newton",
      "aliases": [],
      "categories": [
        "Any Famous Person",
        "Athletes",
        "Football"
      ],
      "letters": {
        "first": "C",
        "last": "N"
      },
      "difficulty": 2,
      "image": null,
      "wiki": null
    },
    {
      "id": "dak-prescott",
      "name": "Dak Prescott",
      "aliases": [],
      "categories": [
        "Any Famous Person",
        "Athletes",
        "Football"
      ],
      "letters": {
        "first": "D",
        "last": "P"
      },
      "difficulty": 2,
      "image": null,
      "wiki": null
    },
    {
      "id": "patrick-mahomes",
      "name": "Patrick Mahomes",
      "aliases": [],
      "categories": [
        "Any Famous Person",
        "Athletes",
        "Football"
      ],
      "letters": {
        "first": "P",
        "last": "M"
      },
      "difficulty": 2,
      "image": null,
      "wiki": null
    }
  ]
}